beam_extended/__init__.py
beam_extended/io/__init__.py
beam_extended/io/mongodbio.py
beam_extended-0.0.7.dist-info/METADATA
beam_extended-0.0.7.dist-info/RECORD
beam_extended-0.0.7.dist-info/WHEEL
beam_extended-0.0.7.dist-info/top_level.txt
